marscan/__init__.py
marscan/main.py
marscan/reporting.py
marscan/scanner/__init__.py
marscan/scanner/base.py
marscan/scanner/connect.py
marscan/scanner/fin.py
marscan/scanner/null.py
marscan/scanner/stealth.py
marscan/scanner/syn.py
marscan/scanner/xmas.py
marscan/utils/__init__.py
marscan/utils/display.py
marscan/utils/logging.py
marscan/utils/ports.py
marscan-2.1.0.dist-info/licenses/LICENSE
marscan-2.1.0.dist-info/METADATA
marscan-2.1.0.dist-info/WHEEL
marscan-2.1.0.dist-info/entry_points.txt
marscan-2.1.0.dist-info/top_level.txt
marscan-2.1.0.dist-info/RECORD
