Metadata-Version: 2.4
Name: marscan
Version: 2.1.0
Summary: A blazing-fast, lightweight Python port scanner for ethical hackers and red teamers.
Author-email: Marwan ALkhatib <marwanalkhatibeh@gmail.com>
License-Expression: MIT
Project-URL: Homepage, https://github.com/MarwanKhatib/MarScan
Keywords: port-scanner,security,network,pentesting,hacking
Classifier: Development Status :: 4 - Beta
Classifier: Intended Audience :: Developers
Classifier: Intended Audience :: Information Technology
Classifier: Topic :: Security
Classifier: Topic :: System :: Networking
Classifier: Programming Language :: Python :: 3
Classifier: Programming Language :: Python :: 3.8
Classifier: Programming Language :: Python :: 3.9
Classifier: Programming Language :: Python :: 3.10
Classifier: Programming Language :: Python :: 3.11
Classifier: Operating System :: OS Independent
Requires-Python: >=3.8
License-File: LICENSE
Requires-Dist: rich>=13.0.0
Requires-Dist: rich-argparse>=1.0.0
Requires-Dist: scapy>=2.4.5
Requires-Dist: pyfiglet>=0.8.post1
Requires-Dist: markdown-it-py>=2.1.0
Requires-Dist: mdurl>=0.1.0
Requires-Dist: Pygments>=2.12.0
Dynamic: license-file
